{
    "identityPoolName": "uberappf9b8e670_identitypool_f9b8e670",
    "allowUnauthenticatedIdentities": false,
    "resourceNameTruncated": "uberapf9b8e670",
    "userPoolName": "uberappf9b8e670_userpool_f9b8e670",
    "autoVerifiedAttributes": [
        "email"
    ],
    "mfaConfiguration": "OFF",
    "mfaTypes": [
        "SMS Text Message"
    ],
    "smsAuthenticationMessage": "Your authentication code is {####}",
    "smsVerificationMessage": "Your verification code is {####}",
    "emailVerificationSubject": "Your verification code",
    "emailVerificationMessage": "Your verification code is {####}",
    "defaultPasswordPolicy": false,
    "passwordPolicyMinLength": 8,
    "passwordPolicyCharacters": [],
    "requiredAttributes": [
        "email"
    ],
    "aliasAttributes": [],
    "userpoolClientGenerateSecret": false,
    "userpoolClientRefreshTokenValidity": 30,
    "userpoolClientWriteAttributes": [
        "email"
    ],
    "userpoolClientReadAttributes": [
        "email"
    ],
    "userpoolClientLambdaRole": "uberapf9b8e670_userpoolclient_lambda_role",
    "userpoolClientSetAttributes": false,
    "sharedId": "f9b8e670",
    "resourceName": "uberappf9b8e670",
    "authSelections": "identityPoolAndUserPool",
    "authRoleArn": {
        "Fn::GetAtt": [
            "AuthRole",
            "Arn"
        ]
    },
    "unauthRoleArn": {
        "Fn::GetAtt": [
            "UnauthRole",
            "Arn"
        ]
    },
    "useDefault": "manual",
    "userPoolGroupList": [],
    "serviceName": "Cognito",
    "usernameCaseSensitive": false,
    "dependsOn": [
        {
            "category": "function",
            "resourceName": "uberappf9b8e670PostConfirmation",
            "triggerProvider": "Cognito",
            "attributes": [
                "Arn",
                "Name"
            ]
        }
    ],
    "userPoolGroups": false,
    "adminQueries": false,
    "triggers": "{\n  \"PostConfirmation\": [\n    \"custom\"\n  ]\n}",
    "hostedUI": true,
    "hostedUIDomainName": "uberapp",
    "authProvidersUserPool": [],
    "hostedUIProviderMeta": "[]",
    "parentStack": {
        "Ref": "AWS::StackId"
    },
    "authTriggerConnections": "[\n  {\n    \"triggerType\": \"PostConfirmation\",\n    \"lambdaFunctionName\": \"uberappf9b8e670PostConfirmation\"\n  }\n]",
    "breakCircularDependency": true,
    "permissions": [],
    "authProviders": [],
    "thirdPartyAuth": false,
    "oAuthMetadata": "{\"AllowedOAuthFlows\":[\"implicit\"],\"AllowedOAuthScopes\":[\"phone\",\"email\",\"openid\",\"profile\",\"aws.cognito.signin.user.admin\"],\"CallbackURLs\":[\"exp://127.0.0.1:19000/\"],\"LogoutURLs\":[\"exp://127.0.0.1:19000/\"]}"
}